{
    "type": "FeatureCollection",
    "name": "CRL-PA-Palau",
    "features": [
        {
            "type": "Feature",
            "properties": {
                "LEVEL4_COD": "CRL-PA",
                "LEVEL4_NAM": "Palau"
            },
            "geometry": {
                "type": "MultiPolygon",
                "coordinates": [
                    [
                        [
                            [
                                134.5313721,
                                7.3544436
                            ],
                            [
                                134.5613708,
                                7.3719435
                            ],
                            [
                                134.6285706,
                                7.4902763
                            ],
                            [
                                134.6497192,
                                7.5780554
                            ],
                            [
                                134.6546936,
                                7.6002769
                            ],
                            [
                                134.6588745,
                                7.6438885
                            ],
                            [
                                134.6588745,
                                7.6574993
                            ],
                            [
                                134.6546936,
                                7.6941652
                            ],
                            [
                                134.6524658,
                                7.705555
                            ],
                            [
                                134.6505432,
                                7.7102776
                            ],
                            [
                                134.6455383,
                                7.7205544
                            ],
                            [
                                134.6388855,
                                7.7272215
                            ],
                            [
                                134.6341553,
                                7.7294436
                            ],
                            [
                                134.6271667,
                                7.7294436
                            ],
                            [
                                134.6216125,
                                7.728055
                            ],
                            [
                                134.6188354,
                                7.7238884
                            ],
                            [
                                134.6174622,
                                7.7186098
                            ],
                            [
                                134.6188354,
                                7.7130547
                            ],
                            [
                                134.6230164,
                                7.7036104
                            ],
                            [
                                134.6327209,
                                7.685832
                            ],
                            [
                                134.638031,
                                7.6708326
                            ],
                            [
                                134.6430359,
                                7.6486101
                            ],
                            [
                                134.6416626,
                                7.6363878
                            ],
                            [
                                134.6355286,
                                7.6288872
                            ],
                            [
                                134.6313477,
                                7.6261101
                            ],
                            [
                                134.6216125,
                                7.6219435
                            ],
                            [
                                134.6052246,
                                7.6180544
                            ],
                            [
                                134.5930176,
                                7.6166658
                            ],
                            [
                                134.5860901,
                                7.6166658
                            ],
                            [
                                134.5621948,
                                7.6133327
                            ],
                            [
                                134.5530396,
                                7.6086102
                            ],
                            [
                                134.5449829,
                                7.5961103
                            ],
                            [
                                134.4852295,
                                7.4380541
                            ],
                            [
                                134.5188599,
                                7.3624992
                            ],
                            [
                                134.5258179,
                                7.3558321
                            ],
                            [
                                134.5313721,
                                7.3544436
                            ]
                        ]
                    ],
                    [
                        [
                            [
                                134.5133057,
                                7.3055544
                            ],
                            [
                                134.5174866,
                                7.308054
                            ],
                            [
                                134.5210876,
                                7.3116655
                            ],
                            [
                                134.5249939,
                                7.3211107
                            ],
                            [
                                134.5249939,
                                7.3277769
                            ],
                            [
                                134.5230408,
                                7.332777
                            ],
                            [
                                134.5174866,
                                7.3408327
                            ],
                            [
                                134.5133057,
                                7.3436108
                            ],
                            [
                                134.4707947,
                                7.3611097
                            ],
                            [
                                134.4655151,
                                7.3624992
                            ],
                            [
                                134.459137,
                                7.3619432
                            ],
                            [
                                134.4538574,
                                7.3605547
                            ],
                            [
                                134.4491272,
                                7.3583326
                            ],
                            [
                                134.4455261,
                                7.3549986
                            ],
                            [
                                134.4449768,
                                7.3422213
                            ],
                            [
                                134.4483032,
                                7.3319435
                            ],
                            [
                                134.4516296,
                                7.3286104
                            ],
                            [
                                134.4558105,
                                7.3272219
                            ],
                            [
                                134.4599609,
                                7.3299999
                            ],
                            [
                                134.4632874,
                                7.3399992
                            ],
                            [
                                134.4660645,
                                7.3441658
                            ],
                            [
                                134.4716187,
                                7.3455544
                            ],
                            [
                                134.4813538,
                                7.3413877
                            ],
                            [
                                134.4894104,
                                7.3361101
                            ],
                            [
                                134.4955139,
                                7.3286104
                            ],
                            [
                                134.5133057,
                                7.3055544
                            ]
                        ]
                    ],
                    [
                        [
                            [
                                134.3777466,
                                7.2158327
                            ],
                            [
                                134.4463501,
                                7.2497206
                            ],
                            [
                                134.4388733,
                                7.2788877
                            ],
                            [
                                134.3482971,
                                7.2722216
                            ],
                            [
                                134.3441162,
                                7.2694435
                            ],
                            [
                                134.3413391,
                                7.2652769
                            ],
                            [
                                134.3407898,
                                7.2605553
                            ],
                            [
                                134.3413391,
                                7.2544441
                            ],
                            [
                                134.3441162,
                                7.2436104
                            ],
                            [
                                134.3510742,
                                7.2299995
                            ],
                            [
                                134.3563538,
                                7.2219439
                            ],
                            [
                                134.3605042,
                                7.2191658
                            ],
                            [
                                134.3707886,
                                7.2158327
                            ],
                            [
                                134.3777466,
                                7.2158327
                            ]
                        ]
                    ],
                    [
                        [
                            [
                                134.3866577,
                                7.1394434
                            ],
                            [
                                134.3927612,
                                7.1402769
                            ],
                            [
                                134.3977661,
                                7.1422215
                            ],
                            [
                                134.4010925,
                                7.1455545
                            ],
                            [
                                134.4002686,
                                7.1516657
                            ],
                            [
                                134.3899841,
                                7.1886101
                            ],
                            [
                                134.387207,
                                7.1924982
                            ],
                            [
                                134.381897,
                                7.1924982
                            ],
                            [
                                134.3768921,
                                7.1905546
                            ],
                            [
                                134.3591309,
                                7.1802769
                            ],
                            [
                                134.3530273,
                                7.1741657
                            ],
                            [
                                134.3538513,
                                7.1680546
                            ],
                            [
                                134.3558044,
                                7.1633329
                            ],
                            [
                                134.3646851,
                                7.1516657
                            ],
                            [
                                134.3721924,
                                7.1455545
                            ],
                            [
                                134.381073,
                                7.1408329
                            ],
                            [
                                134.3866577,
                                7.1394434
                            ]
                        ]
                    ],
                    [
                        [
                            [
                                134.2352295,
                                6.9816656
                            ],
                            [
                                134.2749939,
                                7.0102777
                            ],
                            [
                                134.2769165,
                                7.0149994
                            ],
                            [
                                134.2844238,
                                7.058054
                            ],
                            [
                                134.2844238,
                                7.0633326
                            ],
                            [
                                134.2824707,
                                7.0680552
                            ],
                            [
                                134.2783203,
                                7.0708332
                            ],
                            [
                                134.2730408,
                                7.0708332
                            ],
                            [
                                134.2694397,
                                7.0674992
                            ],
                            [
                                134.2666626,
                                7.0633326
                            ],
                            [
                                134.2268982,
                                6.9941654
                            ],
                            [
                                134.2277527,
                                6.9877768
                            ],
                            [
                                134.2305298,
                                6.9838877
                            ],
                            [
                                134.2352295,
                                6.9816656
                            ]
                        ]
                    ],
                    [
                        [
                            [
                                134.1599731,
                                6.8844442
                            ],
                            [
                                134.1660767,
                                6.8852768
                            ],
                            [
                                134.1708069,
                                6.8872213
                            ],
                            [
                                134.1763611,
                                6.895277
                            ],
                            [
                                134.1783142,
                                6.9069433
                            ],
                            [
                                134.1769104,
                                6.9191656
                            ],
                            [
                                134.1749878,
                                6.9238882
                            ],
                            [
                                134.1688538,
                                6.9313879
                            ],
                            [
                                134.1605225,
                                6.9355545
                            ],
                            [
                                134.1502686,
                                6.937499
                            ],
                            [
                                134.1441345,
                                6.9369431
                            ],
                            [
                                134.1394348,
                                6.934721
                            ],
                            [
                                134.1358032,
                                6.9313879
                            ],
                            [
                                134.1344299,
                                6.9261103
                            ],
                            [
                                134.1338806,
                                6.9130545
                            ],
                            [
                                134.1366577,
                                6.9022217
                            ],
                            [
                                134.1385803,
                                6.8974991
                            ],
                            [
                                134.1447144,
                                6.8899994
                            ],
                            [
                                134.153595,
                                6.8852768
                            ],
                            [
                                134.1599731,
                                6.8844442
                            ]
                        ]
                    ],
                    [
                        [
                            [
                                132.22052,
                                5.2922211
                            ],
                            [
                                132.2266235,
                                5.2927771
                            ],
                            [
                                132.2302551,
                                5.2961102
                            ],
                            [
                                132.2313538,
                                5.3016653
                            ],
                            [
                                132.2302551,
                                5.3072214
                            ],
                            [
                                132.2260742,
                                5.3099985
                            ],
                            [
                                132.2177429,
                                5.3152761
                            ],
                            [
                                132.208313,
                                5.3111095
                            ],
                            [
                                132.208313,
                                5.3058319
                            ],
                            [
                                132.2096863,
                                5.3002768
                            ],
                            [
                                132.2121887,
                                5.2961102
                            ],
                            [
                                132.2157898,
                                5.2927771
                            ],
                            [
                                132.22052,
                                5.2922211
                            ]
                        ]
                    ]
                ]
            }
        }
    ]
}