{
    "type": "FeatureCollection",
    "name": "28-Middle_Atlantic_Ocean",
    "features": [
        {
            "type": "Feature",
            "properties": {
                "LEVEL2_COD": "28",
                "LEVEL2_NAM": "Middle Atlantic Ocean"
            },
            "geometry": {
                "type": "MultiPolygon",
                "coordinates": [
                    [
                        [
                            [
                                -5.6622554,
                                -15.9874948
                            ],
                            [
                                -5.6586554,
                                -15.9838948
                            ],
                            [
                                -5.6469554,
                                -15.9610948
                            ],
                            [
                                -5.6458554,
                                -15.9555948
                            ],
                            [
                                -5.6452554,
                                -15.9399948
                            ],
                            [
                                -5.6713554,
                                -15.9093948
                            ],
                            [
                                -5.6919554,
                                -15.9049948
                            ],
                            [
                                -5.6977554,
                                -15.9038948
                            ],
                            [
                                -5.7041554,
                                -15.9030948
                            ],
                            [
                                -5.7163554,
                                -15.9052948
                            ],
                            [
                                -5.7288554,
                                -15.9138948
                            ],
                            [
                                -5.7486554,
                                -15.9291948
                            ],
                            [
                                -5.7674554,
                                -15.9452948
                            ],
                            [
                                -5.7702554,
                                -15.9494948
                            ],
                            [
                                -5.7924554,
                                -15.9880948
                            ],
                            [
                                -5.7930554,
                                -15.9941948
                            ],
                            [
                                -5.7872554,
                                -16.0091948
                            ],
                            [
                                -5.7705554,
                                -16.0205948
                            ],
                            [
                                -5.7663554,
                                -16.0232948
                            ],
                            [
                                -5.7372554,
                                -16.0096948
                            ],
                            [
                                -5.7288554,
                                -16.0055948
                            ],
                            [
                                -5.7252554,
                                -16.0032948
                            ],
                            [
                                -5.7129554,
                                -15.9928948
                            ],
                            [
                                -5.7105554,
                                -15.9963948
                            ],
                            [
                                -5.7024554,
                                -16.0024948
                            ],
                            [
                                -5.6983554,
                                -16.0049948
                            ],
                            [
                                -5.6622554,
                                -15.9874948
                            ]
                        ]
                    ],
                    [
                        [
                            [
                                -14.3638554,
                                -7.9796948
                            ],
                            [
                                -14.3452554,
                                -7.9752948
                            ],
                            [
                                -14.3402554,
                                -7.9732948
                            ],
                            [
                                -14.3113554,
                                -7.9613948
                            ],
                            [
                                -14.2966554,
                                -7.9485948
                            ],
                            [
                                -14.2930554,
                                -7.9452948
                            ],
                            [
                                -14.2941554,
                                -7.9396948
                            ],
                            [
                                -14.3194554,
                                -7.9180948
                            ],
                            [
                                -14.3558554,
                                -7.8921948
                            ],
                            [
                                -14.3591554,
                                -7.8902948
                            ],
                            [
                                -14.3783554,
                                -7.8830948
                            ],
                            [
                                -14.3819554,
                                -7.8835948
                            ],
                            [
                                -14.3861554,
                                -7.8863948
                            ],
                            [
                                -14.3986554,
                                -7.9019948
                            ],
                            [
                                -14.4058554,
                                -7.9152948
                            ],
                            [
                                -14.4144554,
                                -7.9344948
                            ],
                            [
                                -14.4161554,
                                -7.9399948
                            ],
                            [
                                -14.4122554,
                                -7.9741948
                            ],
                            [
                                -14.4097554,
                                -7.9782948
                            ],
                            [
                                -14.3915554,
                                -7.9840948
                            ],
                            [
                                -14.3638554,
                                -7.9796948
                            ]
                        ]
                    ]
                ]
            }
        }
    ]
}